awkupy/__init__.py
awkupy/_version.py
awkupy/awk.py
awkupy/base.py
awkupy/prompt.py
iawk/__init__.py
iawk/__main__.py
awkupy-0.1.0b0.dist-info/LICENSE
awkupy-0.1.0b0.dist-info/METADATA
awkupy-0.1.0b0.dist-info/WHEEL
awkupy-0.1.0b0.dist-info/entry_points.txt
awkupy-0.1.0b0.dist-info/top_level.txt
awkupy-0.1.0b0.dist-info/RECORD
