Metadata-Version: 2.1
Name: awkupy
Version: 0.1.0b0
Summary: A simple Python interface and IPython/Jupyter magic for AWK
Home-page: https://github.com/ashwinvis/awkupy
Author: Ashwin Vishnu Mohanan
Author-email: ashwinvis+gh@protonmail.com
License: GPL-3.0-or-later
Keywords: awk,iawk,cli,IPython,Jupyter
Platform: UNKNOWN
Classifier: Development Status :: 4 - Beta
Classifier: License :: OSI Approved :: GNU General Public License v3 or later (GPLv3+)
Classifier: Natural Language :: English
Classifier: Programming Language :: Python :: 3
Classifier: Programming Language :: Awk
Classifier: Framework :: IPython
Classifier: Framework :: Jupyter
Classifier: Topic :: Text Processing :: General
Requires-Dist: ipython (>=6.0)
Requires-Dist: typing ; python_version < "3.6"
Requires-Dist: dataclasses ; python_version < "3.7"
Provides-Extra: dev
Requires-Dist: sphinx ; extra == 'dev'
Requires-Dist: recommonmark (>=0.5.0) ; extra == 'dev'
Requires-Dist: sphinx-rtd-theme (==0.4.3) ; extra == 'dev'
Requires-Dist: pytest ; extra == 'dev'
Requires-Dist: jupyter ; extra == 'dev'
Requires-Dist: flake8 ; extra == 'dev'
Requires-Dist: twine ; extra == 'dev'
Requires-Dist: wheel ; extra == 'dev'
Requires-Dist: readme-renderer[md] (==24.0) ; extra == 'dev'
Provides-Extra: docs
Requires-Dist: sphinx ; extra == 'docs'
Requires-Dist: recommonmark (>=0.5.0) ; extra == 'docs'
Requires-Dist: sphinx-rtd-theme (==0.4.3) ; extra == 'docs'
